gg_mcp_demo/__init__.py
gg_mcp_demo-0.1.0.dist-info/WHEEL
gg_mcp_demo-0.1.0.dist-info/entry_points.txt
gg_mcp_demo-0.1.0.dist-info/METADATA
gg_mcp_demo-0.1.0.dist-info/RECORD
