Metadata-Version: 2.3
Name: gg-mcp-demo
Version: 0.1.0
Summary: Add your description here
Author: caoziyang
Author-email: caoziyang <1419608052@qq.com>
Requires-Dist: mcp[cli]>=1.16.0
Requires-Python: >=3.13
